Workbook

Sheet Medalists
A1: City | B1: Year | C1: Sport | D1: Event | E1: Athlete | F1: Gender | G1: Country_Code | H1: Country Name | I1: Medal
A2: Atlanta | B2: 1996 | C2: Rowing | D2: Rowing Men's Lightweight Double Sculls | E2: Pepijn Aardewijn | F2: M | G2: NED | H2: =VLOOKUP(G2,'Country Codes'!$A$2:$B$139,2,FALSE) -> Netherlands | I2: Silver
A3: Atlanta | B3: 1996 | C3: Football | D3: Football Women's Football | E3: Ann Kristin Aarnes | F3: F | G3: NOR | H3: =VLOOKUP(G3,'Country Codes'!$A$2:$B$139,2,FALSE) -> Norway | I3: Bronze
A4: Rio de Janeiro | B4: 2016 | C4: Rowing | D4: Rowing Men's Coxless Pairs | E4: Giovanni Abagnale | F4: M | G4: ITA | H4: =VLOOKUP(G4,'Country Codes'!$A$2:$B$139,2,FALSE) -> Italy | I4: Bronze
A5: Beijing | B5: 2008 | C5: Fencing | D5: Fencing Men's epee, Individual | E5: Jos Luis Abajo Gmez | F5: M | G5: ESP | H5: =VLOOKUP(G5,'Country Codes'!$A$2:$B$139,2,FALSE) -> Spain | I5: Bronze
A6: Rio de Janeiro | B6: 2016 | C6: Taekwondo | D6: Taekwondo Women's Flyweight | E6: Patimat Abakarova | F6: F | G6: AZE | H6: =VLOOKUP(G6,'Country Codes'!$A$2:$B$139,2,FALSE) -> Azerbaijan | I6: Bronze
A7: Beijing | B7: 2008 | C7: Athletics | D7: Athletics Women's Javelin Throw | E7: Mariya Vasilyevna Abakumova (-Tarabina) | F7: F | G7: RUS | H7: =VLOOKUP(G7,'Country Codes'!$A$2:$B$139,2,FALSE) -> Russia | I7: Silver
A8: Beijing | B8: 2008 | C8: Canoeing | D8: Canoeing Men's Kayak Fours, 1,000 metres | E8: Aleksey Aleksandrovich Abalmasov | F8: M | G8: BLR | H8: =VLOOKUP(G8,'Country Codes'!$A$2:$B$139,2,FALSE) -> Belarus | I8: Gold
A9: Rio de Janeiro | B9: 2016 | C9: Handball | D9: Handball Men's Handball | E9: Luc Abalo | F9: M | G9: FRA | H9: =VLOOKUP(G9,'Country Codes'!$A$2:$B$139,2,FALSE) -> France | I9: Silver
A10: Beijing | B10: 2008 | C10: Handball | D10: Handball Men's Handball | E10: Luc Abalo | F10: M | G10: FRA | H10: =VLOOKUP(G10,'Country Codes'!$A$2:$B$139,2,FALSE) -> France | I10: Gold
A11: London | B11: 2012 | C11: Handball | D11: Handball Men's Handball | E11: Luc Abalo | F11: M | G11: FRA | H11: =VLOOKUP(G11,'Country Codes'!$A$2:$B$139,2,FALSE) -> France | I11: Gold
A12: Sydney | B12: 2000 | C12: Football | D12: Football Men's Football | E12: Jouan Patrice Abanda Etong | F12: M | G12: CMR | H12: =VLOOKUP(G12,'Country Codes'!$A$2:$B$139,2,FALSE) -> Cameroon | I12: Gold
A13: Atlanta | B13: 1996 | C13: Water Polo | D13: Water Polo Men's Water Polo | E13: Jos Mara Abarca Plotas | F13: M | G13: ESP | H13: =VLOOKUP(G13,'Country Codes'!$A$2:$B$139,2,FALSE) -> Spain | I13: Gold
... A18917: Sydney | B18917: 2000 | C18917: Athletics | D18917: Athletics Women's 4 x 400 metres Relay | E18917: Olesya Nikolayevna Zykina | F18917: F | G18917: RUS | H18917: =VLOOKUP(G18917,'Country Codes'!$A$2:$B$139,2,FALSE) -> Russia | I18917: Bronze

Sheet Country Codes
A1: Country_Code | B1: Country
A2: AFG | B2: Afghanistan
A3: ALG | B3: Algeria
A4: ARG | B4: Argentina
A5: ARM | B5: Armenia
A6: AUS | B6: Australia
A7: AUT | B7: Austria
A8: AZE | B8: Azerbaijan
A9: BAH | B9: Bahamas
A10: BRN | B10: Bahrain
A11: BAR | B11: Barbados
A12: BLR | B12: Belarus
... A139: ZIM | B139: Zimbabwe

Sheet Pivot Table 1
A3: Count of Medal | B3: Column Labels
A4: Row Labels | B4: Bronze | C4: Gold | D4: Silver | E4: Grand Total
A5: United States | B5: 590 | C5: 1237 | D5: 690 | E5: 2517
A6: Soviet Union | B6: 299 | C6: 432 | D6: 287 | E6: 1018
A7: Australia | B7: 398 | C7: 257 | D7: 334 | E7: 989
A8: Germany | B8: 362 | C8: 330 | D8: 246 | E8: 938
A9: China | B9: 256 | C9: 334 | D9: 316 | E9: 906
A10: Russia | B10: 322 | C10: 294 | D10: 269 | E10: 885
A11: Great Britain | B11: 261 | C11: 231 | D11: 243 | E11: 735
A12: East Germany | B12: 151 | C12: 296 | D12: 193 | E12: 640
A13: France | B13: 228 | C13: 203 | D13: 196 | E13: 627
A14: Italy | B14: 229 | C14: 166 | D14: 227 | E14: 622
A15: Grand Total | B15: 3096 | C15: 3780 | D15: 3001 | E15: 9877

Sheet Pivot Table 2
A1: Medal | B1: (All)
A3: Count of Medal | B3: Column Labels
B4: F | C4: M | D4: Grand Total
A5: Row Labels
A6: Australia | B6: 457 | C6: 532 | D6: 989
A7: China | B7: 600 | C7: 306 | D7: 906
A8: East Germany | B8: 317 | C8: 323 | D8: 640
A9: France | B9: 150 | C9: 477 | D9: 627
A10: Germany | B10: 403 | C10: 535 | D10: 938
A11: Great Britain | B11: 240 | C11: 495 | D11: 735
A12: Italy | B12: 128 | C12: 494 | D12: 622
A13: Russia | B13: 445 | C13: 440 | D13: 885
A14: Soviet Union | B14: 328 | C14: 690 | D14: 1018
A15: United States | B15: 1212 | C15: 1305 | D15: 2517
A16: Grand Total | B16: 4280 | C16: 5597 | D16: 9877

Sheet Pivot Table 3
A1: Country Name | B1: (All)
A3: Count of Gender | B3: Column Labels
A4: Row Labels | B4: F | C4: M | D4: Grand Total
A5: 1976 | B5: 388 | C5: 915 | D5: 1303
A6: 1980 | B6: 432 | C6: 945 | D6: 1377
A7: 1984 | B7: 492 | C7: 971 | D7: 1463
A8: 1988 | B8: 552 | C8: 1024 | D8: 1576
A9: 1992 | B9: 509 | C9: 1014 | D9: 1523
A10: 1996 | B10: 684 | C10: 1033 | D10: 1717
A11: 2000 | B11: 877 | C11: 1116 | D11: 1993
A12: 2004 | B12: 897 | C12: 1103 | D12: 2000
A13: 2008 | B13: 924 | C13: 1111 | D13: 2035
A14: 2012 | B14: 901 | C14: 1014 | D14: 1915
A15: 2016 | B15: 967 | C15: 1047 | D15: 2014
A16: Grand Total | B16: 7623 | C16: 11293 | D16: 18916
